poff/__init__.py
poff/_version.py
poff/base62.py
poff/cli.py
poff/models.py
poff/views.py
poff/templates/base.html
poff/templates/domains.html
poff/tests/__init__.py
poff/tests/test_dispatch.py
poff/tests/test_domains.py
poff/tests/test_dyndns.py
poff/tests/test_records.py
poff-1.6.3.dist-info/LICENSE
poff-1.6.3.dist-info/METADATA
poff-1.6.3.dist-info/WHEEL
poff-1.6.3.dist-info/entry_points.txt
poff-1.6.3.dist-info/top_level.txt
poff-1.6.3.dist-info/RECORD
